{"classes": [
    {
      "name": "Мастер – класс по Филетеадо ",
      "description": "Мастер класс по Fileteado c мате или вином. Очень аутентичный опыт в матерской. Художник на английском (при необходимости будет перевод на русский) расскажет о традициях Fileteado (объект культурного наследия ЮНЕСКО), каждый из участников распишет для меня калобасу для матэ или именную доску. Вы увезете из Аргентины неповторимый сувенир, сделанный своими руками. ",
      "price": "Стоимость 65 USD / персона",
      "nav": "fileteado",
      "link":  "https://www.instagram.com/reel/C0WcI86LSbY/?utm_source=ig_web_copy_link&igshid=MzRlODBiNWFlZA=="
    },
    {
      "name": "Незабываемый день на традиционной эстанции",
      "description": "Мастер класс по Fileteado c мате или вином. Очень аутентичный опыт в матерской. Художник на английском (при необходимости будет перевод на русский) расскажет о традициях Fileteado (объект культурного наследия ЮНЕСКО), каждый из участников распишет для меня калобасу для матэ или именную доску. Вы увезете из Аргентины неповторимый сувенир, сделанный своими руками. ",
      "price": "Стоимость 65 USD / персона",
      "nav": "fileteado",
      "link":  "https://www.instagram.com/reel/C0WcI86LSbY/?utm_source=ig_web_copy_link&igshid=MzRlODBiNWFlZA=="
    }
]
}
